setup.py
eddy_dsnd_probability/Binomialdistribution.py
eddy_dsnd_probability/Gaussiandistribution.py
eddy_dsnd_probability/Generaldistribution.py
eddy_dsnd_probability/__init__.py
eddy_dsnd_probability.egg-info/PKG-INFO
eddy_dsnd_probability.egg-info/SOURCES.txt
eddy_dsnd_probability.egg-info/dependency_links.txt
eddy_dsnd_probability.egg-info/not-zip-safe
eddy_dsnd_probability.egg-info/top_level.txt