Metadata-Version: 1.0
Name: eddy-dsnd-probability
Version: 0.1
Summary: Gaussian and Binomial distributions
Home-page: UNKNOWN
Author: Edward Amankwah
Author-email: eaakwasi@yahoo.ca
License: UNKNOWN
Platform: UNKNOWN
